characterController/Animator.py
characterController/Config.py
characterController/Mover.py
characterController/PhysicsBullet.py
characterController/PhysicsInternal.py
characterController/PlayerController.py
characterController/__init__.py
characterController/cameraPlugins/CameraFirstPerson.py
characterController/cameraPlugins/CameraThirdPerson.py
characterController/cameraPlugins/__init__.py
characterController/controlPlugins/__init__.py
characterController/controlPlugins/plug01WallRun.py
characterController/controlPlugins/plug02LedgeGrab.py
characterController/controlPlugins/plug03WallCollisionAvoidance.py
characterController/controlPlugins/plug04Climb.py
characterController/inputPlugins/__init__.py
characterController/inputPlugins/inputMapping.py
characterController/inputPlugins/plugGamepad.py
characterController/inputPlugins/plugKeyboard.py
characterController/inputPlugins/plugWiiRemote.py
controlPlugins/__init__.py
controlPlugins/plug01WallRun.py
controlPlugins/plug02LedgeGrab.py
controlPlugins/plug03WallCollisionAvoidance.py
controlPlugins/plug04Climb.py
inputPlugins/__init__.py
inputPlugins/inputMapping.py
inputPlugins/plugGamepad.py
inputPlugins/plugKeyboard.py
inputPlugins/plugWiiRemote.py
panda3d_character_controller-20.11.1.dist-info/LICENSE
panda3d_character_controller-20.11.1.dist-info/METADATA
panda3d_character_controller-20.11.1.dist-info/WHEEL
panda3d_character_controller-20.11.1.dist-info/top_level.txt
panda3d_character_controller-20.11.1.dist-info/RECORD
