Metadata-Version: 2.1
Name: panda3d-character-controller
Version: 20.11.1
Summary: Extensive character control system to be used with the Panda3D engine
Home-page: https://github.com/fireclawthefox/panda3d-character-controller
Author: Fireclaw
Author-email: fireclawthefox@gmail.com
License: UNKNOWN
Platform: UNKNOWN
Classifier: Programming Language :: Python :: 3
Classifier: License :: OSI Approved :: BSD License
Classifier: Operating System :: OS Independent
Classifier: Development Status :: 5 - Production/Stable
Classifier: Intended Audience :: Developers
Classifier: Intended Audience :: End Users/Desktop
Classifier: Topic :: Games/Entertainment
Requires-Python: >=3.6
Requires-Dist: panda3d
